immunewatch_clustcr-1.0.1.dist-info/licenses/LICENSE
imw_clustcr/__init__.py
imw_clustcr/chem_properties.py
imw_clustcr/exception.py
imw_clustcr/clustering/__init__.py
imw_clustcr/clustering/clustering.py
imw_clustcr/clustering/methods.py
imw_clustcr/clustering/metrics.py
imw_clustcr/clustering/multirepertoire_cluster_matrix.py
imw_clustcr/clustering/tools.py
imw_clustcr/faiss_clustering/__init__.py
imw_clustcr/faiss_clustering/src/__init__.py
imw_clustcr/faiss_clustering/src/evaluate.py
imw_clustcr/faiss_clustering/src/cluster/FaissClustering.py
imw_clustcr/faiss_clustering/src/cluster/__init__.py
imw_clustcr/faiss_clustering/src/cluster/tools.py
imw_clustcr/faiss_clustering/src/distance/DistancePairs.py
imw_clustcr/faiss_clustering/src/distance/__init__.py
imw_clustcr/faiss_clustering/src/distance/tools.py
imw_clustcr/faiss_clustering/src/io/__init__.py
imw_clustcr/faiss_clustering/src/io/datasets.py
imw_clustcr/faiss_clustering/src/io/input.py
imw_clustcr/faiss_clustering/src/io/output.py
imw_clustcr/faiss_clustering/src/plots/__init__.py
imw_clustcr/faiss_clustering/src/plots/benchmark_time.py
imw_clustcr/faiss_clustering/src/plots/compare_clusters.py
imw_clustcr/faiss_clustering/src/plots/distance_accuracy.py
imw_clustcr/faiss_clustering/src/plots/measures.py
imw_clustcr/faiss_clustering/src/plots/size_frequencies.py
imw_clustcr/faiss_clustering/src/plots/weighting.py
imw_clustcr/faiss_clustering/src/profile/__init__.py
imw_clustcr/faiss_clustering/src/profile/atchley.py
imw_clustcr/faiss_clustering/src/profile/profile.py
imw_clustcr/faiss_clustering/src/profile/properties.py
imw_clustcr/faiss_clustering/src/profile/z_scores.py
imw_clustcr/input/__init__.py
imw_clustcr/input/adaptive_imgt_mapping.csv
imw_clustcr/input/adaptive_to_imgt.py
imw_clustcr/input/airr.py
imw_clustcr/input/alphabeta_gammadelta_db.tsv
imw_clustcr/input/datasets.py
imw_clustcr/input/immuneaccess.py
imw_clustcr/input/tcrex.py
imw_clustcr/input/tenx.py
imw_clustcr/input/tools.py
imw_clustcr/input/vdjdb.py
immunewatch_clustcr-1.0.1.dist-info/METADATA
immunewatch_clustcr-1.0.1.dist-info/WHEEL
immunewatch_clustcr-1.0.1.dist-info/top_level.txt
immunewatch_clustcr-1.0.1.dist-info/RECORD
