Metadata-Version: 2.4
Name: immunewatch-clustcr
Version: 1.0.1
Summary: a Python interface for rapid clustering of large sets of CDR3 sequences
Author-email: Max Van Houcke <max@immunewatch.com>
License: MIT
Project-URL: Homepage, https://www.immunewatch.com/
Keywords: TCR,clustering,CDR3,immunology
Classifier: Programming Language :: Python :: 3
Classifier: Programming Language :: Python :: 3.7
Classifier: Programming Language :: Python :: 3.8
Classifier: Programming Language :: Python :: 3.9
Classifier: Programming Language :: Python :: 3.10
Classifier: Programming Language :: Python :: 3.11
Classifier: License :: OSI Approved :: MIT License
Classifier: Operating System :: OS Independent
Requires-Python: >=3.7
License-File: LICENSE
Requires-Dist: numpy
Requires-Dist: pandas
Requires-Dist: networkx
Requires-Dist: scikit-learn
Requires-Dist: markov_clustering
Requires-Dist: parmap
Requires-Dist: python-louvain
Requires-Dist: matplotlib
Requires-Dist: faiss-cpu
Requires-Dist: scipy==1.8
Provides-Extra: dev
Requires-Dist: pytest>=6.0; extra == "dev"
Requires-Dist: pytest-cov; extra == "dev"
Requires-Dist: flake8; extra == "dev"
Provides-Extra: test
Requires-Dist: pytest>=6.0; extra == "test"
Requires-Dist: pytest-cov; extra == "test"
Dynamic: license-file
